pycryptex/__init__.py
pycryptex/main.py
pycryptex/crypto/__init__.py
pycryptex/crypto/aes.py
pycryptex/crypto/common.py
pycryptex/crypto/rsa.py
pycryptex/internal/__init__.py
pycryptex/internal/decorators.py
pycryptex/internal/utils.py
pycryptex-0.5.0.dist-info/LICENSE
pycryptex-0.5.0.dist-info/METADATA
pycryptex-0.5.0.dist-info/WHEEL
pycryptex-0.5.0.dist-info/entry_points.txt
pycryptex-0.5.0.dist-info/top_level.txt
pycryptex-0.5.0.dist-info/RECORD
