Metadata-Version: 2.1
Name: pycryptex
Version: 0.5.0
Summary: Python CLI application to easily encrypt and decrypt file and folders. Easy and fast for the lovers of the CLI.
Home-page: https://github.com/mas2020-python/pycryptex
Author: mas2020
Author-email: andrea.genovesi@gmail.com
License: MIT
Platform: UNKNOWN
Classifier: Programming Language :: Python :: 3
Classifier: License :: OSI Approved :: MIT License
Classifier: Operating System :: OS Independent
Requires-Python: >=3.6, <4
Requires-Dist: click (==7.1.2)
Requires-Dist: pycryptodome (==3.9.8)
Requires-Dist: toml (==0.10.1)
Requires-Dist: tqdm (==4.50.2)
